RequestSoup.py
manager.py
RequestSoup-1.0.4.dist-info/LICENSE
RequestSoup-1.0.4.dist-info/METADATA
RequestSoup-1.0.4.dist-info/WHEEL
RequestSoup-1.0.4.dist-info/top_level.txt
RequestSoup-1.0.4.dist-info/RECORD
