Metadata-Version: 2.1
Name: RequestSoup
Version: 1.0.4
Summary: A wrapper created to make using requests and BeautifulSoup in conjunction easier
Home-page: https://github.com/ArnavChawla/RequestSoup
Author: Arnav Chawla
Author-email: arnavchawla23@gmail.com
License: UNKNOWN
Platform: UNKNOWN
Classifier: License :: OSI Approved :: MIT License
Requires-Dist: requests
Requires-Dist: bs4
